consultant/__init__.py
consultant/app.py
consultant/args.py
consultant/config.py
consultant/logger.py
consultant-0.0.0.dist-info/METADATA
consultant-0.0.0.dist-info/WHEEL
consultant-0.0.0.dist-info/entry_points.txt
consultant-0.0.0.dist-info/top_level.txt
consultant-0.0.0.dist-info/RECORD
